{
  "id": "matix",
  "title": "MATIX Bike",
  "industry": "Produkcja rowerów",
  "category": "inne",
  "description": "Producent rowerow trojkolowych premium, modeli elektrycznych i pojazdow rehabilitacyjnych.",
  "tools": "HTML · CSS · JavaScript",
  "timeToDeliver": "4 dni",
  "previewUrl": "https://kamillimak.github.io/Projects/projects/matix/",
  "liveUrl": "",
  "featured": false,
  "colorAccent": "#B8E040",
  "colorBg": "#0F140A",
  "tags": ["HTML", "Rowery", "Produkt premium"],
  "dateAdded": "2026-06",
  "versions": ["index.html", "v2.html"]
}
